{
	"@context": "https://hubmapconsortium.github.io/ccf-ontology/ccf-context.jsonld",
	"@type": "SpatialEntity",
	"creator": "Antara Bhavsar",
	"creator_first_name": "Antara",
	"creator_last_name": "Bhavsar",
	"creator_orcid": "https://orcid.org/0009-0006-6491-6503",
	"dimension_units": "millimeter",
	"placement": {
		"@context": "https://hubmapconsortium.github.io/ccf-ontology/ccf-context.jsonld",
		"@type": "SpatialPlacement",
		"target": "https://purl.humanatlas.io/ref-organ/lung-female/v1.4#primary",
		"scaling_units": "ratio",
		"rotation_order": "XYZ",
		"rotation_units": "degree",
		"translation_units": "millimeter",
		"@id": "https://purl.humanatlas.io/millitome/lung-female-large/v1.0#RLL-14A7_placement",
		"placement_date": "2026-04-10",
		"x_scaling": 1.0,
		"y_scaling": 1.0,
		"z_scaling": 0.9999999999999999,
		"x_rotation": 96.10934567259933,
		"y_rotation": -7.5460334791601955,
		"z_rotation": -51.33422238556767,
		"x_translation": 3.012084959018672,
		"y_translation": 84.85769019855293,
		"z_translation": 64.22763330616033
	},
	"@id": "https://purl.humanatlas.io/millitome/lung-female-large/v1.0#RLL-14A7",
	"label": "RLL-14A7",
	"creation_date": "2026-04-10",
	"x_dimension": 4.842424346876414,
	"y_dimension": 15.198935284254453,
	"z_dimension": 19.15437346335644
}